jydb/__init__.py
jydb/db.py
jydb-1.0.1.dist-info/METADATA
jydb-1.0.1.dist-info/WHEEL
jydb-1.0.1.dist-info/top_level.txt
jydb-1.0.1.dist-info/RECORD
