Metadata-Version: 2.1
Name: jydb
Version: 1.0.1
Summary: 基于pymysql的便捷数据库查询
Home-page: UNKNOWN
Author: JY
Author-email: your-email@example.com
License: UNKNOWN
Platform: UNKNOWN
Requires-Dist: pymysql
